README.md
setup.py
pumpkin_supmcu/kubos/__init__.py
pumpkin_supmcu/kubos/kubos.py
pumpkin_supmcu_kubos.egg-info/PKG-INFO
pumpkin_supmcu_kubos.egg-info/SOURCES.txt
pumpkin_supmcu_kubos.egg-info/dependency_links.txt
pumpkin_supmcu_kubos.egg-info/not-zip-safe
pumpkin_supmcu_kubos.egg-info/requires.txt
pumpkin_supmcu_kubos.egg-info/top_level.txt