Metadata-Version: 2.1
Name: pumpkin-supmcu-kubos
Version: 0.0.3
Summary: A library to interface with Pumpkin SupMCU modules via I2C with the KubOS I2C HAL library package.
Home-page: https://gitlab.com/pumpkin-space-systems/public/pumpkin-supmcu-kubos
Author: James Womack
Author-email: info@pumpkininc.com
License: UNKNOWN
Platform: UNKNOWN
Classifier: Programming Language :: Python :: 3
Classifier: License :: OSI Approved :: MIT License
Classifier: Operating System :: OS Independent
Requires-Python: >=3.7
